{
  "name": "canmatrix",
  "summary": null,
  "language": "python",
  "tags": [
    "math"
  ],
  "chunks": [
    {
      "chunk_id": "canmatrix::chunk_0",
      "text": "Canmatrix implements a \"Python Can Matrix Object\" which describes the can-communication\nand the needed objects (Boardunits, Frames, Signals, Values, ...) Canmatrix also includes\ntwo Tools (canconvert and cancompare) for converting and comparing CAN databases.\nThere are also some extract and merge options for dealing with can databases.\n\n**supported file formats for import:**\n\n**supported file formats for export:**",
      "word_count": 57
    }
  ],
  "usage_description": "This library is used to create and manipulate Can Matrix Objects that describe CAN communication, including importing and exporting various database formats. It also provides tools for converting and comparing CAN databases, as well as extracting and merging data within these databases."
}